config_with_yaml/__init__.py
config_with_yaml/config.py
config_with_yaml/properties.py
config_with_yaml-0.1.0.dist-info/LICENSE
config_with_yaml-0.1.0.dist-info/METADATA
config_with_yaml-0.1.0.dist-info/WHEEL
config_with_yaml-0.1.0.dist-info/top_level.txt
config_with_yaml-0.1.0.dist-info/RECORD
