Metadata-Version: 2.1
Name: config_with_yaml
Version: 0.1.0
Summary: Loads configurations from yaml files
Home-page: https://github.com/aitormf/config_with_yaml
Author: aitormf
Author-email: aitor.martinez.fernandez@gmail.com
License: UNKNOWN
Platform: UNKNOWN
Classifier: Programming Language :: Python :: 3
Classifier: License :: OSI Approved :: GNU General Public License v3 (GPLv3)
Classifier: Operating System :: OS Independent
Requires-Python: >=3.6
